arcade_clickup_api/__init__.py
arcade_clickup_api/moar/Clickup.json
arcade_clickup_api/moar/openapi.json
arcade_clickup_api/tools/__init__.py
arcade_clickup_api/tools/request_body_schemas.py
arcade_clickup_api/wrapper_tools/AddChatViewComment.json
arcade_clickup_api/wrapper_tools/AddChecklistItemClickup.json
arcade_clickup_api/wrapper_tools/AddChecklistToTask.json
arcade_clickup_api/wrapper_tools/AddCommentToList.json
arcade_clickup_api/wrapper_tools/AddFolderlessListToSpace.json
arcade_clickup_api/wrapper_tools/AddGuestToFolder.json
arcade_clickup_api/wrapper_tools/AddGuestToList.json
arcade_clickup_api/wrapper_tools/AddSpaceTaskTag.json
arcade_clickup_api/wrapper_tools/AddSpaceView.json
arcade_clickup_api/wrapper_tools/AddTagToTask.json
arcade_clickup_api/wrapper_tools/AddTagToTimeEntry.json
arcade_clickup_api/wrapper_tools/AddTargetToGoal.json
arcade_clickup_api/wrapper_tools/AddTaskComment.json
arcade_clickup_api/wrapper_tools/AddTaskToClickupList.json
arcade_clickup_api/wrapper_tools/AddViewToClickupList.json
arcade_clickup_api/wrapper_tools/AddViewToFolder.json
arcade_clickup_api/wrapper_tools/ClickupLegacyTimeTracking.json
arcade_clickup_api/wrapper_tools/ConfigureWorkspaceGuest.json
arcade_clickup_api/wrapper_tools/CreateClickupList.json
arcade_clickup_api/wrapper_tools/CreateFolderFromTemplate.json
arcade_clickup_api/wrapper_tools/CreateFolderInSpace.json
arcade_clickup_api/wrapper_tools/CreateListFromFolderTemplate.json
arcade_clickup_api/wrapper_tools/CreateListFromTemplate.json
arcade_clickup_api/wrapper_tools/CreateNewClickupTask.json
arcade_clickup_api/wrapper_tools/CreateSpaceInWorkspace.json
arcade_clickup_api/wrapper_tools/CreateTaskFromTemplate.json
arcade_clickup_api/wrapper_tools/CreateTeamView.json
arcade_clickup_api/wrapper_tools/CreateThreadedComment.json
arcade_clickup_api/wrapper_tools/CreateTimeEntry.json
arcade_clickup_api/wrapper_tools/CreateUserGroup.json
arcade_clickup_api/wrapper_tools/CreateWorkspaceGoal.json
arcade_clickup_api-1.0.0.dist-info/METADATA
arcade_clickup_api-1.0.0.dist-info/WHEEL
arcade_clickup_api-1.0.0.dist-info/entry_points.txt
arcade_clickup_api-1.0.0.dist-info/RECORD
