Metadata-Version: 2.4
Name: arcade_clickup_api
Version: 1.0.0
Summary: Tools that enable LLMs to interact directly with the clickup API.
Author-email: support@arcade.dev
Requires-Python: >=3.10
Requires-Dist: arcade-tdk<4.0.0,>=3.0.0
Requires-Dist: httpx[http2]<1.0.0,>=0.27.2
Requires-Dist: jsonschema<5.0.0,>=4.0.0
Provides-Extra: dev
Requires-Dist: arcade-mcp[all]<2.0.0,>=1.2.0; extra == 'dev'
Requires-Dist: arcade-serve<4.0.0,>=3.0.0; extra == 'dev'
Requires-Dist: mypy<1.6.0,>=1.5.1; extra == 'dev'
Requires-Dist: pre-commit<3.5.0,>=3.4.0; extra == 'dev'
Requires-Dist: pytest-asyncio<0.25.0,>=0.24.0; extra == 'dev'
Requires-Dist: pytest-cov<4.1.0,>=4.0.0; extra == 'dev'
Requires-Dist: pytest-mock<3.12.0,>=3.11.1; extra == 'dev'
Requires-Dist: pytest<8.4.0,>=8.3.0; extra == 'dev'
Requires-Dist: ruff<0.8.0,>=0.7.4; extra == 'dev'
Requires-Dist: tox<4.12.0,>=4.11.1; extra == 'dev'
